{
  "exported_at": "2026-03-11T14:34:00Z",
  "criteria_version": "2.0.0",
  "total_tracked": 8,
  "min_score": 7,
  "coins": [
    {
      "id": 2,
      "chain": "solana",
      "token_address": "J8PSdNP3QewKq2Z1JJJFDMaqF7KcaiJhR7gbr5KZpump",
      "name": "Tung Tung Tung Sahur",
      "symbol": "TRIPLET",
      "added_at": "2026-02-24T09:38:16.790Z",
      "score": 8,
      "status": "active",
      "dexscreener": "https://dexscreener.com/solana/3kfcgj5r3zshw8htdbzjsrrksrymkvsmfhc4vo4iddxd",
      "entry_price": 0.000551,
      "mc_at_add": 587000.0,
      "ath_price": 0.002798,
      "ath_at": "2026-03-09T22:16:36.919Z",
      "outcome_72h": "normal",
      "outcome_14d": null,
      "outcome_final": null,
      "category": "meme",
      "notes": "BOUGHT | 1.25139 SOL \u2192 191123.07 TRIPLET | 2026-03-01 09:07 | Phantom @xlgeneration",
      "contract": "J8PSdNP3QewKq2Z1JJJFDMaqF7KcaiJhR7gbr5KZpump",
      "is_bought": 1,
      "buy_amount_sol": 1.25139,
      "buy_tokens": 191123.07,
      "buy_date": "2026-03-01T09:07:00Z"
    },
    {
      "id": 1,
      "chain": "solana",
      "token_address": "6ngSN9zA32mShK5itfNVPsJvwADfiSDxiDbTUpwzpump",
      "name": "\u5495\u5495\u560e\u560e",
      "symbol": "gugugaga",
      "added_at": "2026-03-06 04:54:10",
      "score": 9,
      "status": "active",
      "dexscreener": "https://dexscreener.com/solana/h1yp9d9vecg46feffpk3c5dlfawh9weus6jurh71dky",
      "entry_price": 8.729e-05,
      "mc_at_add": 87293.0,
      "ath_price": 0.0001353,
      "ath_at": "2026-03-10T20:28:53.926Z",
      "outcome_72h": null,
      "outcome_14d": null,
      "outcome_final": null,
      "category": "meme",
      "notes": "Major anime character meme (BanG Dream MyGO). Wikipedia entry, 45.4M BiliBili views, real-world impact (Xpark penguin naming Dec 2024). Cultural phenomenon comparable to MOODENG.",
      "contract": "6ngSN9zA32mShK5itfNVPsJvwADfiSDxiDbTUpwzpump",
      "v2_score": 4,
      "is_bought": 0
    },
    {
      "id": 2,
      "chain": "solana",
      "token_address": "DKqgMMtEiAMXR8iz4tpVXgnmL8Bgzbu4XPyUrZWrpump",
      "name": "ruck",
      "symbol": "ruck",
      "added_at": "2026-03-02T21:23:22.677Z",
      "score": 9,
      "status": "active",
      "dexscreener": "https://dexscreener.com/solana/55hkiqhswup2z8ggvoi7e4tjnzgnjw1ttahmb2kdhage",
      "entry_price": 0.000231,
      "mc_at_add": 229841.0,
      "ath_price": 0.000231,
      "ath_at": "2026-03-06T04:16:35.697Z",
      "outcome_72h": null,
      "outcome_14d": null,
      "outcome_final": null,
      "category": "meme",
      "notes": null,
      "contract": "DKqgMMtEiAMXR8iz4tpVXgnmL8Bgzbu4XPyUrZWrpump",
      "v2_score": 3,
      "is_bought": 0
    },
    {
      "id": 7,
      "chain": "solana",
      "token_address": "8whH5tErGbDEiSBKWAHigJe3dXFa6YwdMDXESNrVpump",
      "name": "Pok\u00e9mon Pokopia",
      "symbol": "Pok\u00e9mon Pokopia",
      "added_at": "2026-03-02T17:38:20.670Z",
      "score": 10,
      "status": "active",
      "dexscreener": "https://dexscreener.com/solana/cc1quww2z6kcntf9haoo4xwbjxpqsr25n6nzsqrwtews",
      "entry_price": 8.531e-05,
      "mc_at_add": 85299.0,
      "ath_price": 8.531e-05,
      "ath_at": "2026-03-06T10:16:38.062Z",
      "outcome_72h": null,
      "outcome_14d": null,
      "outcome_final": null,
      "category": "meme",
      "notes": null,
      "contract": "8whH5tErGbDEiSBKWAHigJe3dXFa6YwdMDXESNrVpump",
      "v2_score": 3,
      "is_bought": 0
    },
    {
      "id": 6,
      "chain": "solana",
      "token_address": "FqeKiQrMmTq6wmuBwo3i6sum8AhaGfvnZAmWEcVEpump",
      "name": "Aced Brett",
      "symbol": "Aced Brett",
      "added_at": "2026-03-03T10:53:18.106Z",
      "score": 9,
      "status": "active",
      "dexscreener": "https://dexscreener.com/solana/7cks5ovpgcyz4znz3hbtrzngucgfqfn6az9ffdm2fcov",
      "entry_price": 9.482e-05,
      "mc_at_add": 94829.0,
      "ath_price": 9.63e-05,
      "ath_at": "2026-03-07T12:16:36.111Z",
      "outcome_72h": "normal",
      "outcome_14d": null,
      "outcome_final": null,
      "category": "meme",
      "notes": null,
      "contract": "FqeKiQrMmTq6wmuBwo3i6sum8AhaGfvnZAmWEcVEpump",
      "v2_score": 1,
      "is_bought": 0
    },
    {
      "id": 3,
      "chain": "solana",
      "token_address": "ctQPRPpLY52CeEfmJqUEhYQ6SmMVHitkU3KKEDUpump",
      "name": "#SendBarron",
      "symbol": "Barron",
      "added_at": "2026-03-01 21:38:54",
      "score": 9,
      "status": "active",
      "dexscreener": "https://dexscreener.com/solana/85jy4gkkgyh1gn42ur3kfbztexovbnggtriqfqtgn1dm",
      "entry_price": 0.0004291,
      "mc_at_add": 429198.0,
      "ath_price": 0.0002709,
      "ath_at": "2026-03-01T22:12:32.791Z",
      "outcome_72h": "fail",
      "outcome_14d": null,
      "outcome_final": null,
      "category": "meme",
      "notes": null,
      "contract": "ctQPRPpLY52CeEfmJqUEhYQ6SmMVHitkU3KKEDUpump",
      "v2_score": 0,
      "is_bought": 0
    },
    {
      "id": 4,
      "chain": "solana",
      "token_address": "5P4sZjYRbaawFZ6FyFgeaq1PYk57Bj5GL4UHXgnjpump",
      "name": "Chinese Brainrot",
      "symbol": "Chinese Brainrot",
      "added_at": "2026-03-03T21:23:17.981Z",
      "score": 12,
      "status": "active",
      "dexscreener": "https://dexscreener.com/solana/eztqanuzsb71gvtkimp9xsqt6olk8buxy1fqgcutlrgh",
      "entry_price": 7.284e-05,
      "mc_at_add": 72573.0,
      "ath_price": 7.284e-05,
      "ath_at": "2026-03-06T00:16:35.849Z",
      "outcome_72h": "normal",
      "outcome_14d": null,
      "outcome_final": null,
      "category": "meme",
      "notes": null,
      "contract": "5P4sZjYRbaawFZ6FyFgeaq1PYk57Bj5GL4UHXgnjpump",
      "v2_score": 0,
      "is_bought": 0
    },
    {
      "id": 8,
      "chain": "solana",
      "token_address": "7NoFtDpmQvE9JsRv7o6zgYZJBEcixWumJaZsDoyrpump",
      "name": "\u661f\u661f",
      "symbol": "\u661f\u661f",
      "added_at": "2026-02-24T07:23:20.512Z",
      "score": 8,
      "status": "active",
      "dexscreener": "https://dexscreener.com/solana/avsfihlzhjk6llvplrvdez9jvpv7bpgnpgh5qysbmtp1",
      "entry_price": 0.00019085,
      "mc_at_add": 250411.0,
      "ath_price": 0.000253,
      "ath_at": "2026-02-25T01:12:06.894Z",
      "outcome_72h": "normal",
      "outcome_14d": "fail",
      "outcome_final": "fail",
      "category": "meme",
      "notes": null,
      "contract": "7NoFtDpmQvE9JsRv7o6zgYZJBEcixWumJaZsDoyrpump",
      "v2_score": 0,
      "is_bought": 0
    }
  ],
  "sol_free": 1.28316,
  "sol_usd": 111.19
}