{
  "date": "2026-02-13",
  "followers": 942,
  "media_count": 408,
  "recent_posts": [
    {
      "type": "VIDEO",
      "caption_start": "Robot Dog vs Pom",
      "date": "2026-02-13",
      "likes": 1,
      "comments": 0,
      "url": "https://www.instagram.com/reel/DUtRbbBitrr/"
    },
    {
      "type": "IMAGE",
      "caption_start": "Zhouzhuang Squad",
      "date": "2026-02-12",
      "likes": 8,
      "comments": 6,
      "url": "https://www.instagram.com/p/DUqslq6EtfS/"
    },
    {
      "type": "IMAGE",
      "caption_start": "Protective Mode",
      "date": "2026-02-11",
      "likes": 12,
      "comments": 4,
      "url": "https://www.instagram.com/p/DUoHysqEkL3/"
    },
    {
      "type": "IMAGE",
      "caption_start": "Short King",
      "date": "2026-02-11",
      "likes": 6,
      "comments": 3,
      "url": "https://www.instagram.com/p/DUmZ7zSEl3p/"
    },
    {
      "type": "VIDEO",
      "caption_start": "First Snow 2026",
      "date": "2026-02-11",
      "likes": 8,
      "comments": 0,
      "url": "https://www.instagram.com/reel/DUmRohpAcyi/"
    }
  ]
}
